{"name":"Cinephiles","tagline":"a movie discovery & sharing web application","body":"# [Cinephiles](https://cinephiles.herokuapp.com/) <-- Try It !\r\n\r\n## Summary\r\n\r\nCinephiles is an visual discovery and sharing web application all about Movies. User can search, browse, watch, and buy their favorite movies anywhere, anytime.\r\n\r\n## Technology\r\n\r\n* HTML 5\r\n* CSS 3\r\n* Ruby with Sinatra framework\r\n* JavaScript, jQuery & AJAX\r\n* Heroku\r\n* Google API\r\n* OMDB API\r\n* BCrypt User Authentication\r\n\r\n## Releases\r\n\r\n### Beta 1.0\r\n* Added Amazon.com link to watch the movie via Amazon Instant Video or buy blu-ray/DVD disc\r\n* Updated UI layout\r\n* Updated HTML & CSS\r\n\r\n### Beta 1.1\r\n* Updated UI 2.0\r\n* Added popular movies on homepage\r\n\r\n### Beta 1.2\r\n* Added about page\r\n* Added result page: has poster & other details/ links to amazon\r\n\r\n### Beta 1.3\r\n* Added Popular page\r\n* Added Coming Soon page\r\n* Added Theater page with Google Map API\r\n\r\n### Beta 1.4\r\n* Added Background video\r\n* Fixed broken poster link\r\n\r\n### Beta 1.5\r\n* Users can register\r\n* Users can login\r\n\r\n### Upcoming\r\n\r\n* Fix redirecting error\r\n* Users can 'actual' register\r\n* Users can 'actual' login\r\n* Add Users profile page\r\n* Add Users bookmark page\r\n* Add Contact Me form\r\n* Random generate different `popular/coming soon movies\r\n* Users can share favorite movies\r\n* Create API for 3rd party use\r\n\r\n## Issue\r\n\r\n* Sometimes, the poster may not be able to be shown due to redirecting error\r\n\r\n\r\n","google":"UA-51174308-1","note":"Don't delete this file! It's used internally to help with page regeneration."}